aash/__init__.py
aash/aash.py
aash-0.0.2.dist-info/METADATA
aash-0.0.2.dist-info/WHEEL
aash-0.0.2.dist-info/RECORD
